[
    {
        "actionName": "Action",
        "steps": [
            {
                "stepId": "STEP1",
                "stepName": "Url: WebTours",
                "infFile": "t2.inf",
                "time": 1685975756062
            },
            {
                "stepId": "STEP2",
                "stepName": "Submit Data: login.pl",
                "infFile": "t3.inf",
                "time": 1685975756334
            },
            {
                "stepId": "STEP3",
                "stepName": "Url: Search Flights Button",
                "infFile": "t4.inf",
                "time": 1685975756787
            },
            {
                "stepId": "STEP4",
                "stepName": "Submit Data: reservations.pl",
                "infFile": "t6.inf",
                "time": 1685975756998
            },
            {
                "stepId": "STEP5",
                "stepName": "Submit Data: reservations.pl_2",
                "infFile": "t7.inf",
                "time": 1685975757151
            },
            {
                "stepId": "STEP6",
                "stepName": "Url: SignOff Button",
                "infFile": "t8.inf",
                "time": 1685975757346
            }
        ],
        "transactions": [
            {
                "transactionName": "goToSite",
                "rawStartTime": 1685975755772,
                "rawEndTime": 1685975756070,
                "thinkTime": 0.0,
                "wastedTime": 0.09079623222351074
            },
            {
                "transactionName": "login",
                "rawStartTime": 1685975756101,
                "rawEndTime": 1685975756555,
                "thinkTime": 0.0,
                "wastedTime": 0.005788564682006836
            },
            {
                "transactionName": "click_flights",
                "rawStartTime": 1685975756582,
                "rawEndTime": 1685975756800,
                "thinkTime": 0.0,
                "wastedTime": 0.009666919708251953
            },
            {
                "transactionName": "search_flights",
                "rawStartTime": 1685975756846,
                "rawEndTime": 1685975757017,
                "thinkTime": 0.0,
                "wastedTime": 0.006789445877075195
            },
            {
                "transactionName": "select_ticket",
                "rawStartTime": 1685975757048,
                "rawEndTime": 1685975757172,
                "thinkTime": 0.0,
                "wastedTime": 0.004827976226806641
            },
            {
                "transactionName": "logout",
                "rawStartTime": 1685975757203,
                "rawEndTime": 1685975757357,
                "thinkTime": 0.0,
                "wastedTime": 0.004509687423706055
            },
            {
                "transactionName": "03_SearchTicketNoPayment",
                "rawStartTime": 1685975755756,
                "rawEndTime": 1685975757374,
                "thinkTime": 0.0,
                "wastedTime": 0.12237882614135742
            }
        ]
    }
]